{
  "title": "장비 계산용 시트",
  "rows": [
    {
      "Skill Lv": 0,
      "장비 필요량 (누적)": "",
      "C": "",
      "D": "",
      "E": "",
      "F": "",
      "G": "",
      "H": "",
      "I": "",
      "J": "",
      "크레딧 필요량(누적)": "",
      "티어내 Lv업 비용": "",
      "티어업 비용": ""
    },
    {
      "Skill Lv": 1,
      "장비 필요량 (누적)": "",
      "C": "",
      "D": "",
      "E": "",
      "F": "",
      "G": "",
      "H": "",
      "I": "",
      "J": "",
      "크레딧 필요량(누적)": 1524,
      "티어내 Lv업 비용": 1524,
      "티어업 비용": 0
    },
    {
      "Skill Lv": 2,
      "장비 필요량 (누적)": 15,
      "C": "",
      "D": "",
      "E": "",
      "F": "",
      "G": "",
      "H": "",
      "I": "",
      "J": "",
      "크레딧 필요량(누적)": 10388,
      "티어내 Lv업 비용": 7364,
      "티어업 비용": 1500
    },
    {
      "Skill Lv": 3,
      "장비 필요량 (누적)": 15,
      "C": 20,
      "D": "",
      "E": "",
      "F": "",
      "G": "",
      "H": "",
      "I": "",
      "J": "",
      "크레딧 필요량(누적)": 42212,
      "티어내 Lv업 비용": 21824,
      "티어업 비용": 10000
    },
    {
      "Skill Lv": 4,
      "장비 필요량 (누적)": 25,
      "C": 20,
      "D": 30,
      "E": "",
      "F": "",
      "G": "",
      "H": "",
      "I": "",
      "J": "",
      "크레딧 필요량(누적)": 116516,
      "티어내 Lv업 비용": 49304,
      "티어업 비용": 25000
    },
    {
      "Skill Lv": 5,
      "장비 필요량 (누적)": 40,
      "C": 40,
      "D": 30,
      "E": 35,
      "F": "",
      "G": "",
      "H": "",
      "I": "",
      "J": "",
      "크레딧 필요량(누적)": 235820,
      "티어내 Lv업 비용": 69304,
      "티어업 비용": 50000
    },
    {
      "Skill Lv": 6,
      "장비 필요량 (누적)": 40,
      "C": 45,
      "D": 45,
      "E": 35,
      "F": 40,
      "G": "",
      "H": "",
      "I": "",
      "J": "",
      "크레딧 필요량(누적)": 405024,
      "티어내 Lv업 비용": 94204,
      "티어업 비용": 75000
    },
    {
      "Skill Lv": 7,
      "장비 필요량 (누적)": 40,
      "C": 45,
      "D": 50,
      "E": 50,
      "F": 40,
      "G": 40,
      "H": "",
      "I": "",
      "J": "",
      "크레딧 필요량(누적)": 629588,
      "티어내 Lv업 비용": 124564,
      "티어업 비용": 100000
    },
    {
      "Skill Lv": 8,
      "장비 필요량 (누적)": 40,
      "C": 45,
      "D": 50,
      "E": 55,
      "F": 55,
      "G": 40,
      "H": 40,
      "I": "",
      "J": "",
      "크레딧 필요량(누적)": 915512,
      "티어내 Lv업 비용": 160924,
      "티어업 비용": 125000
    },
    {
      "Skill Lv": 9,
      "장비 필요량 (누적)": 40,
      "C": 45,
      "D": 50,
      "E": 55,
      "F": 65,
      "G": 55,
      "H": 40,
      "I": 50,
      "J": "",
      "크레딧 필요량(누적)": 1269356,
      "티어내 Lv업 비용": 203844,
      "티어업 비용": 150000
    },
    {
      "Skill Lv": 10,
      "장비 필요량 (누적)": 40,
      "C": 45,
      "D": 50,
      "E": 55,
      "F": 65,
      "G": 65,
      "H": 60,
      "I": 50,
      "J": 60,
      "크레딧 필요량(누적)": 1698220,
      "티어내 Lv업 비용": 253864,
      "티어업 비용": 175000
    }
  ]
}