{
  "name": "e_x_digit1",
  "window_rect": {
    "left": 0,
    "top": 0,
    "width": 2560,
    "height": 1440
  },
  "points_screen": [
    {
      "x": 1127,
      "y": 1212
    },
    {
      "x": 1155,
      "y": 1212
    },
    {
      "x": 1148,
      "y": 1236
    },
    {
      "x": 1120,
      "y": 1236
    }
  ],
  "points_client": [
    {
      "x": 1127,
      "y": 1212
    },
    {
      "x": 1155,
      "y": 1212
    },
    {
      "x": 1148,
      "y": 1236
    },
    {
      "x": 1120,
      "y": 1236
    }
  ],
  "points_ratio": [
    {
      "x": 0.440234,
      "y": 0.841667
    },
    {
      "x": 0.451172,
      "y": 0.841667
    },
    {
      "x": 0.448437,
      "y": 0.858333
    },
    {
      "x": 0.4375,
      "y": 0.858333
    }
  ],
  "shape": "parallelogram"
}